e7epd/__init__.py
e7epd/__main__.py
e7epd/cli.py
e7epd/e707pd_spec.py
e7epd/e7epd.py
e7epd-0.6.0.dist-info/LICENSE.md
e7epd-0.6.0.dist-info/METADATA
e7epd-0.6.0.dist-info/WHEEL
e7epd-0.6.0.dist-info/entry_points.txt
e7epd-0.6.0.dist-info/top_level.txt
e7epd-0.6.0.dist-info/RECORD
