Metadata-Version: 2.1
Name: e7epd
Version: 0.6.0
Summary: An electronics parts management software
Home-page: https://github.com/Electro707/ee-parts-database
Author: Electro707 (Jamal Bouajjaj)
Author-email: develop@electro707.com
License: GNU General Public License v3 (GPLv3)
Project-URL: Documentation, https://e7epd.readthedocs.io
Project-URL: Bug Tracker, https://github.com/Electro707/ee-parts-database/issues
Classifier: Programming Language :: Python :: 3
Classifier: License :: OSI Approved :: GNU General Public License v3 (GPLv3)
Classifier: Operating System :: OS Independent
License-File: LICENSE.md
Requires-Dist: rich
Requires-Dist: engineering-notation
Requires-Dist: questionary
Requires-Dist: SQLAlchemy
Requires-Dist: alembic
Requires-Dist: requests
